nimbus_inference/__init__.py
nimbus_inference/cell_analyzer.py
nimbus_inference/example_dataset.py
nimbus_inference/nimbus.py
nimbus_inference/trainer.py
nimbus_inference/unet.py
nimbus_inference/utils.py
nimbus_inference/viewer_widget.py
nimbus_inference-0.0.5.dist-info/METADATA
nimbus_inference-0.0.5.dist-info/WHEEL
nimbus_inference-0.0.5.dist-info/licenses/LICENSE
nimbus_inference-0.0.5.dist-info/RECORD
