Metadata-Version: 2.4
Name: Nimbus-Inference
Version: 0.0.5
Summary: A model for classification of cells into marker positive / negative
Project-URL: Documentation, https://Nimbus-Inference.readthedocs.io/
Project-URL: Source, https://github.com/angelolab/Nimbus-Inference
Project-URL: Home-page, https://github.com/angelolab/Nimbus-Inference
Author: Lorenz Rumberger, Noah F. Greenwald
Maintainer-email: Lorenz Rumberger <jlrumber@stanford.edu>, "Noah F. Greenwald" <nfgreen@stanford.edu>, Sricharan Reddy Varra <srivarra@stanford.edu>
License: MIT License
License-File: LICENSE
Requires-Python: >=3.9
Requires-Dist: alpineer
Requires-Dist: datasets<4.0
Requires-Dist: huggingface-hub
Requires-Dist: ipython
Requires-Dist: ipywidgets
Requires-Dist: joblib
Requires-Dist: kornia
Requires-Dist: lmdb
Requires-Dist: mpl-interactions
Requires-Dist: natsort
Requires-Dist: numpy<2.0.0
Requires-Dist: opencv-python-headless
Requires-Dist: pandas
Requires-Dist: pathlib
Requires-Dist: pyometiff
Requires-Dist: scikit-image
Requires-Dist: session-info
Requires-Dist: torch>=2.2.0
Requires-Dist: tqdm
Requires-Dist: zarr
Provides-Extra: dev
Requires-Dist: pre-commit; extra == 'dev'
Requires-Dist: twine>=4.0.2; extra == 'dev'
Provides-Extra: doc
Requires-Dist: docutils!=0.18.*,!=0.19.*,>=0.8; extra == 'doc'
Requires-Dist: ipykernel; extra == 'doc'
Requires-Dist: ipython; extra == 'doc'
Requires-Dist: pandas; extra == 'doc'
Requires-Dist: sphinx-autodoc-typehints; extra == 'doc'
Requires-Dist: sphinx-copybutton; extra == 'doc'
Requires-Dist: sphinx-rtd-theme>1; extra == 'doc'
Requires-Dist: sphinx>=5; extra == 'doc'
Requires-Dist: sphinxext-opengraph; extra == 'doc'
Provides-Extra: test
Requires-Dist: coverage; extra == 'test'
Requires-Dist: coveralls[toml]; extra == 'test'
Requires-Dist: pytest; extra == 'test'
Requires-Dist: pytest-cov; extra == 'test'
Requires-Dist: pytest-socket; extra == 'test'
